README.md
setup.py
RemovePinyinTones/RemovePinyinTones.py
RemovePinyinTones/__init__.py
RemovePinyinTones.egg-info/PKG-INFO
RemovePinyinTones.egg-info/SOURCES.txt
RemovePinyinTones.egg-info/dependency_links.txt
RemovePinyinTones.egg-info/not-zip-safe
RemovePinyinTones.egg-info/top_level.txt