Metadata-Version: 1.0
Name: RemovePinyinTones
Version: 0.1
Summary: remove the pinyin tone from pinyin string
Home-page: UNKNOWN
Author: UNKNOWN
Author-email: UNKNOWN
License: UNKNOWN
Platform: UNKNOWN
